koheesio/__about__.py
koheesio/__init__.py
koheesio/context.py
koheesio/logger.py
koheesio/asyncio/__init__.py
koheesio/asyncio/http.py
koheesio/integrations/__init__.py
koheesio/integrations/box.py
koheesio/integrations/snowflake/__init__.py
koheesio/integrations/snowflake/test_utils.py
koheesio/integrations/spark/__init__.py
koheesio/integrations/spark/sftp.py
koheesio/integrations/spark/snowflake.py
koheesio/integrations/spark/databricks/__init__.py
koheesio/integrations/spark/databricks/secrets.py
koheesio/integrations/spark/databricks/utils.py
koheesio/integrations/spark/dq/__init__.py
koheesio/integrations/spark/dq/spark_expectations.py
koheesio/integrations/spark/tableau/__init__.py
koheesio/integrations/spark/tableau/hyper.py
koheesio/integrations/spark/tableau/server.py
koheesio/models/__init__.py
koheesio/models/reader.py
koheesio/models/sql.py
koheesio/notifications/__init__.py
koheesio/notifications/slack.py
koheesio/pandas/__init__.py
koheesio/pandas/readers/__init__.py
koheesio/pandas/readers/excel.py
koheesio/secrets/__init__.py
koheesio/spark/__init__.py
koheesio/spark/delta.py
koheesio/spark/etl_task.py
koheesio/spark/snowflake.py
koheesio/spark/functions/__init__.py
koheesio/spark/readers/__init__.py
koheesio/spark/readers/delta.py
koheesio/spark/readers/dummy.py
koheesio/spark/readers/excel.py
koheesio/spark/readers/file_loader.py
koheesio/spark/readers/hana.py
koheesio/spark/readers/jdbc.py
koheesio/spark/readers/kafka.py
koheesio/spark/readers/memory.py
koheesio/spark/readers/metastore.py
koheesio/spark/readers/rest_api.py
koheesio/spark/readers/snowflake.py
koheesio/spark/readers/spark_sql_reader.py
koheesio/spark/readers/teradata.py
koheesio/spark/readers/databricks/__init__.py
koheesio/spark/readers/databricks/autoloader.py
koheesio/spark/transformations/__init__.py
koheesio/spark/transformations/arrays.py
koheesio/spark/transformations/camel_to_snake.py
koheesio/spark/transformations/cast_to_datatype.py
koheesio-0.10.6.dist-info/METADATA
koheesio-0.10.6.dist-info/WHEEL
koheesio-0.10.6.dist-info/licenses/LICENSE.txt
koheesio-0.10.6.dist-info/RECORD
