Metadata-Version: 2.4
Name: koheesio
Version: 0.10.6
Summary: The steps-based Koheesio framework
Project-URL: Documentation, https://github.com/Nike-Inc/koheesio#readme
Project-URL: Issues, https://github.com/Nike-Inc/koheesio/issues
Project-URL: Source, https://github.com/Nike-Inc/koheesio
Project-URL: Project, https://github.com/orgs/Nike-Inc/projects/4
Author: Danny Meijer, Mikita Sakalouski, Maxim Mityutko, Tone Vanden Bergh, Pariksheet Barapatre, Riccardo Iacomini
License-Expression: Apache-2.0
License-File: LICENSE.txt
Classifier: Development Status :: 5 - Production/Stable
Classifier: Intended Audience :: Developers
Classifier: License :: OSI Approved :: Apache Software License
Classifier: Natural Language :: English
Classifier: Operating System :: OS Independent
Classifier: Programming Language :: Python
Classifier: Programming Language :: Python :: 3.9
Classifier: Programming Language :: Python :: 3.10
Classifier: Programming Language :: Python :: 3.11
Classifier: Programming Language :: Python :: 3.12
Classifier: Programming Language :: Python :: Implementation :: CPython
Classifier: Programming Language :: Python :: Implementation :: PyPy
Classifier: Topic :: Software Development :: Libraries :: Python Modules
Requires-Python: <3.13,>=3.9
Requires-Dist: cryptography>=42.0.4
Requires-Dist: jsonpickle>2.1.0
Requires-Dist: pydantic>=2
Requires-Dist: python-decouple>=3.8
Requires-Dist: pytz>=2023.3
Requires-Dist: pyyaml>=6.0
Requires-Dist: tomli>=2.0.1
Provides-Extra: async
Requires-Dist: nest-asyncio>=1.6.0; extra == 'async'
Provides-Extra: async-http
Requires-Dist: aiohttp-retry>=2.8.3; extra == 'async-http'
Requires-Dist: aiohttp[speedups]>=3.9.5; extra == 'async-http'
Requires-Dist: nest-asyncio>=1.6.0; extra == 'async-http'
Provides-Extra: box
Requires-Dist: boxsdk[jwt]==3.8.1; extra == 'box'
Provides-Extra: delta
Requires-Dist: delta-spark>=2.2; extra == 'delta'
Provides-Extra: dev
Requires-Dist: colorama; extra == 'dev'
Requires-Dist: mypy; extra == 'dev'
Requires-Dist: pylint; extra == 'dev'
Requires-Dist: ruff; extra == 'dev'
Requires-Dist: types-pyyaml; extra == 'dev'
Requires-Dist: types-requests; extra == 'dev'
Provides-Extra: docs
Requires-Dist: black; extra == 'docs'
Requires-Dist: markdown>=3.5.2; extra == 'docs'
Requires-Dist: mike>=2.0.0; extra == 'docs'
Requires-Dist: mkdocs-click>=0.8.0; extra == 'docs'
Requires-Dist: mkdocs-gen-files>=0.5.0; extra == 'docs'
Requires-Dist: mkdocs-git-revision-date-localized-plugin>=1.2.2; extra == 'docs'
Requires-Dist: mkdocs-glightbox>=0.3.4; extra == 'docs'
Requires-Dist: mkdocs-include-markdown-plugin>=6.0.4; extra == 'docs'
Requires-Dist: mkdocs-literate-nav>=0.6.0; extra == 'docs'
Requires-Dist: mkdocs-material-extensions>=1.3.1; extra == 'docs'
Requires-Dist: mkdocs-material>=9.5.13; extra == 'docs'
Requires-Dist: mkdocs-redirects>=1.2.1; extra == 'docs'
Requires-Dist: mkdocs-section-index>=0.3.8; extra == 'docs'
Requires-Dist: mkdocs>=1.5.3; extra == 'docs'
Requires-Dist: mkdocstrings-python>=1.7.5; extra == 'docs'
Requires-Dist: pygments>=2.17.2; extra == 'docs'
Requires-Dist: pymdown-extensions>=10.7.0; extra == 'docs'
Provides-Extra: excel
Requires-Dist: openpyxl>=3.0.0; extra == 'excel'
Provides-Extra: pandas
Requires-Dist: numpy<2.0.0; extra == 'pandas'
Requires-Dist: pandas-stubs; extra == 'pandas'
Requires-Dist: pandas>=1.3; extra == 'pandas'
Requires-Dist: setuptools; extra == 'pandas'
Provides-Extra: pyspark
Requires-Dist: pyarrow>13; extra == 'pyspark'
Requires-Dist: pyspark>=3.2.0; extra == 'pyspark'
Provides-Extra: pyspark-connect
Requires-Dist: pyspark[connect]>=3.5; extra == 'pyspark-connect'
Provides-Extra: se
Requires-Dist: spark-expectations<2.3.0,>=2.2.1; extra == 'se'
Provides-Extra: sftp
Requires-Dist: paramiko>=2.6.0; extra == 'sftp'
Provides-Extra: snowflake
Requires-Dist: snowflake-connector-python>=3.12.0; extra == 'snowflake'
Provides-Extra: tableau
Requires-Dist: tableauhyperapi>=0.0.19484; extra == 'tableau'
Requires-Dist: tableauserverclient>=0.25; extra == 'tableau'
Provides-Extra: test
Requires-Dist: aioresponses; extra == 'test'
Requires-Dist: chispa; extra == 'test'
Requires-Dist: coverage[toml]; extra == 'test'
Requires-Dist: flaky; extra == 'test'
Requires-Dist: freezegun; extra == 'test'
Requires-Dist: pytest; extra == 'test'
Requires-Dist: pytest-asyncio; extra == 'test'
Requires-Dist: pytest-cov; extra == 'test'
Requires-Dist: pytest-mock; extra == 'test'
Requires-Dist: pytest-order; extra == 'test'
Requires-Dist: pytest-randomly; extra == 'test'
Requires-Dist: pytest-sftpserver; extra == 'test'
Requires-Dist: pytest-xdist; extra == 'test'
Requires-Dist: requests-mock; extra == 'test'
Requires-Dist: responses; extra == 'test'
Requires-Dist: time-machine; extra == 'test'
